ants_client-3.0.5.data/scripts/ants
ants_client-3.0.5.data/scripts/ants_inventory_ad
ants_client-3.0.5.data/scripts/ants_inventory_default
antslib/__init__.py
antslib/argparser.py
antslib/configer.py
antslib/logger.py
antslib/macos_prefs.py
antslib/pre_run_checker.py
antslib/etc/ants.cfg
antslib/inventory/__init__.py
antslib/inventory/helper.py
antslib/plugins/callback/ants_logstash.py
ants_client-3.0.5.dist-info/LICENSE
ants_client-3.0.5.dist-info/METADATA
ants_client-3.0.5.dist-info/WHEEL
ants_client-3.0.5.dist-info/top_level.txt
ants_client-3.0.5.dist-info/RECORD
