Metadata-Version: 2.1
Name: ants-client
Version: 3.0.5
Summary: ANTS Framework client
Home-page: https://ants-framework.github.io/
Author: ['Balz Aschwanden', 'Jan Welker', 'Client Services Team of the University of Basel IT Services']
Author-email: balz.aschwanden@unibas.ch, jan.welker@unibas.ch
License: GPLv3
Keywords: client antsFramework ansible ansiblePull unibas
Platform: UNKNOWN
Classifier: Development Status :: 5 - Production/Stable
Classifier: Environment :: Console
Classifier: Intended Audience :: System Administrators
Classifier: License :: OSI Approved :: GNU General Public License v3 (GPLv3)
Classifier: Operating System :: MacOS
Classifier: Operating System :: POSIX :: Linux
Classifier: Topic :: Documentation :: Sphinx
Classifier: Topic :: System :: Systems Administration
Classifier: Programming Language :: Python :: 2.7
Requires-Python: >=3.6
Requires-Dist: ansible (==2.10.1)
Requires-Dist: ldap3 (==2.8.1)
Requires-Dist: python-logstash (==0.4.6)
Requires-Dist: configparser (==5.0.1)
Requires-Dist: future (==0.18.2)
Requires-Dist: certifi (==2020.6.20)
